pinarkive_client.py
pinarkive_sdk_py-2.3.1.dist-info/METADATA
pinarkive_sdk_py-2.3.1.dist-info/WHEEL
pinarkive_sdk_py-2.3.1.dist-info/top_level.txt
pinarkive_sdk_py-2.3.1.dist-info/RECORD
