Metadata-Version: 2.4
Name: pinarkive-sdk-py
Version: 2.3.1
Summary: Python SDK for the Pinarkive API v2.3.1 - Easy IPFS file management with directory DAG uploads, file renaming, and enhanced API key management. Includes type hints for better IDE support.
Author: ITCS VIP, Joel_da
License: MIT
Project-URL: Homepage, https://github.com/pinarkive/pinarkive-sdk-py
Project-URL: Repository, https://github.com/pinarkive/pinarkive-sdk-py.git
Requires-Python: >=3.7
Requires-Dist: requests>=2.31.0
